odoo/addons/project_task_tag/README.rst
odoo/addons/project_task_tag/__init__.py
odoo/addons/project_task_tag/__manifest__.py
odoo/addons/project_task_tag/i18n/it.po
odoo/addons/project_task_tag/i18n/project_task_tag.pot
odoo/addons/project_task_tag/readme/CONTRIBUTORS.md
odoo/addons/project_task_tag/readme/DESCRIPTION.md
odoo/addons/project_task_tag/static/description/icon.png
odoo/addons/project_task_tag/static/description/index.html
odoo/addons/project_task_tag/views/project_task.xml
odoo_addon_project_task_tag-18.0.1.0.0.2.dist-info/METADATA
odoo_addon_project_task_tag-18.0.1.0.0.2.dist-info/WHEEL
odoo_addon_project_task_tag-18.0.1.0.0.2.dist-info/top_level.txt
odoo_addon_project_task_tag-18.0.1.0.0.2.dist-info/RECORD
